opentelemetry/shim/opencensus/__init__.py
opentelemetry/shim/opencensus/_patch.py
opentelemetry/shim/opencensus/_shim_span.py
opentelemetry/shim/opencensus/_shim_tracer.py
opentelemetry/shim/opencensus/py.typed
opentelemetry/shim/opencensus/version/__init__.py
opentelemetry_opencensus_shim-0.60b1.dist-info/METADATA
opentelemetry_opencensus_shim-0.60b1.dist-info/WHEEL
opentelemetry_opencensus_shim-0.60b1.dist-info/licenses/LICENSE
opentelemetry_opencensus_shim-0.60b1.dist-info/RECORD
