Metadata-Version: 2.4
Name: opentelemetry-opencensus-shim
Version: 0.60b1
Summary: OpenCensus Shim for OpenTelemetry
Project-URL: Homepage, https://github.com/open-telemetry/opentelemetry-python/tree/main/shim/opentelemetry-opencensus-shim
Project-URL: Repository, https://github.com/open-telemetry/opentelemetry-python
Author-email: OpenTelemetry Authors <cncf-opentelemetry-contributors@lists.cncf.io>
License-Expression: Apache-2.0
License-File: LICENSE
Classifier: Development Status :: 4 - Beta
Classifier: Framework :: OpenTelemetry
Classifier: Intended Audience :: Developers
Classifier: Programming Language :: Python
Classifier: Programming Language :: Python :: 3
Classifier: Programming Language :: Python :: 3.9
Classifier: Programming Language :: Python :: 3.10
Classifier: Programming Language :: Python :: 3.11
Classifier: Programming Language :: Python :: 3.12
Classifier: Programming Language :: Python :: 3.13
Classifier: Typing :: Typed
Requires-Python: >=3.9
Requires-Dist: opencensus>=0.11.0
Requires-Dist: opentelemetry-api~=1.3
Requires-Dist: wrapt~=1.0
